testa/__init__.py
testa/tools.py
testa/tools2.py
testa/ta/__init__.py
testa/ta/core.py
testa/tb/__init__.py
testa/tb/utilities.py
mysetup_test-0.0.2.dist-info/LICENSE
mysetup_test-0.0.2.dist-info/METADATA
mysetup_test-0.0.2.dist-info/WHEEL
mysetup_test-0.0.2.dist-info/top_level.txt
mysetup_test-0.0.2.dist-info/RECORD
