Metadata-Version: 2.1
Name: mysetup-test
Version: 0.0.2
Summary: This is a mini but function completed neural networks framework
Home-page: UNKNOWN
Author: zidanewenqsh
Author-email: zidanewenqsh@163.com
License: UNKNOWN
Platform: UNKNOWN
Classifier: Programming Language :: Python :: 3
Classifier: License :: OSI Approved :: MIT License
Classifier: Operating System :: OS Independent
Requires-Python: >=3.6
License-File: LICENSE
